[
    {
        "ModelYear": 2016,
        "Make": "ACURA",
        "VehicleId": 0
    },
    {
        "ModelYear": 2016,
        "Make": "ALFA ROMEO",
        "VehicleId": 0
    },
    {
        "ModelYear": 2016,
        "Make": "AUDI",
        "VehicleId": 0
    },
    {
        "ModelYear": 2016,
        "Make": "BENTLEY",
        "VehicleId": 0
    },
    {
        "ModelYear": 2016,
        "Make": "BMW",
        "VehicleId": 0
    },
    {
        "ModelYear": 2016,
        "Make": "BUICK",
        "VehicleId": 0
    },
    {
        "ModelYear": 2016,
        "Make": "CADILLAC",
        "VehicleId": 0
    },
    {
        "ModelYear": 2016,
        "Make": "CHEVROLET",
        "VehicleId": 0
    },
    {
        "ModelYear": 2016,
        "Make": "CHRYSLER",
        "VehicleId": 0
    },
    {
        "ModelYear": 2016,
        "Make": "DODGE",
        "VehicleId": 0
    },
    {
        "ModelYear": 2016,
        "Make": "FIAT",
        "VehicleId": 0
    },
    {
        "ModelYear": 2016,
        "Make": "FORD",
        "VehicleId": 0
    },
    {
        "ModelYear": 2016,
        "Make": "GMC",
        "VehicleId": 0
    },
    {
        "ModelYear": 2016,
        "Make": "HONDA",
        "VehicleId": 0
    },
    {
        "ModelYear": 2016,
        "Make": "HYUNDAI",
        "VehicleId": 0
    },
    {
        "ModelYear": 2016,
        "Make": "INFINITI",
        "VehicleId": 0
    },
    {
        "ModelYear": 2016,
        "Make": "JAGUAR",
        "VehicleId": 0
    },
    {
        "ModelYear": 2016,
        "Make": "JEEP",
        "VehicleId": 0
    },
    {
        "ModelYear": 2016,
        "Make": "KIA",
        "VehicleId": 0
    },
    {
        "ModelYear": 2016,
        "Make": "LAND ROVER",
        "VehicleId": 0
    },
    {
        "ModelYear": 2016,
        "Make": "LEXUS",
        "VehicleId": 0
    },
    {
        "ModelYear": 2016,
        "Make": "LINCOLN",
        "VehicleId": 0
    },
    {
        "ModelYear": 2016,
        "Make": "MASERATI",
        "VehicleId": 0
    },
    {
        "ModelYear": 2016,
        "Make": "MAZDA",
        "VehicleId": 0
    },
    {
        "ModelYear": 2016,
        "Make": "MERCEDES-BENZ",
        "VehicleId": 0
    },
    {
        "ModelYear": 2016,
        "Make": "MERCEDES-MAYBACH",
        "VehicleId": 0
    },
    {
        "ModelYear": 2016,
        "Make": "MINI",
        "VehicleId": 0
    },
    {
        "ModelYear": 2016,
        "Make": "MITSUBISHI",
        "VehicleId": 0
    },
    {
        "ModelYear": 2016,
        "Make": "NISSAN",
        "VehicleId": 0
    },
    {
        "ModelYear": 2016,
        "Make": "PORSCHE",
        "VehicleId": 0
    },
    {
        "ModelYear": 2016,
        "Make": "RAM",
        "VehicleId": 0
    },
    {
        "ModelYear": 2016,
        "Make": "ROLLS-ROYCE",
        "VehicleId": 0
    },
    {
        "ModelYear": 2016,
        "Make": "SMART",
        "VehicleId": 0
    },
    {
        "ModelYear": 2016,
        "Make": "SUBARU",
        "VehicleId": 0
    },
    {
        "ModelYear": 2016,
        "Make": "TESLA",
        "VehicleId": 0
    },
    {
        "ModelYear": 2016,
        "Make": "TOYOTA",
        "VehicleId": 0
    },
    {
        "ModelYear": 2016,
        "Make": "VOLKSWAGEN",
        "VehicleId": 0
    },
    {
        "ModelYear": 2016,
        "Make": "VOLVO",
        "VehicleId": 0
    }
]